{
    "caller-id": "7e07d8f0f5", 
    "turns": [
        {
            "turn-index": 0, 
            "goal-labels": {
                "pricerange": "cheap", 
                "area": "west"
            }, 
            "transcription": "cheap restaurant in the west part of town", 
            "method-label": "byconstraints", 
            "audio-file": "pt344x_0001145_0001377.wav", 
            "requested-slots": [], 
            "semantics": {
                "json": [
                    {
                        "slots": [
                            [
                                "pricerange", 
                                "cheap"
                            ]
                        ], 
                        "act": "inform"
                    }, 
                    {
                        "slots": [
                            [
                                "area", 
                                "west"
                            ]
                        ], 
                        "act": "inform"
                    }
                ], 
                "cam": "inform(pricerange=cheap,type=restaurant,area=west)"
            }
        }, 
        {
            "turn-index": 1, 
            "goal-labels": {
                "pricerange": "cheap", 
                "area": "west"
            }, 
            "transcription": "thank you", 
            "method-label": "byconstraints", 
            "audio-file": "pt344x_0002101_0002124.wav", 
            "requested-slots": [], 
            "semantics": {
                "json": [
                    {
                        "slots": [], 
                        "act": "thankyou"
                    }
                ], 
                "cam": "thankyou()"
            }
        }, 
        {
            "turn-index": 2, 
            "goal-labels": {
                "pricerange": "cheap", 
                "area": "west"
            }, 
            "transcription": "phone number", 
            "method-label": "byconstraints", 
            "audio-file": "pt344x_0002182_0002233.wav", 
            "requested-slots": [
                "phone"
            ], 
            "semantics": {
                "json": [
                    {
                        "slots": [
                            [
                                "slot", 
                                "phone"
                            ]
                        ], 
                        "act": "request"
                    }
                ], 
                "cam": "request(phone)"
            }
        }, 
        {
            "turn-index": 3, 
            "goal-labels": {
                "pricerange": "cheap", 
                "area": "west"
            }, 
            "transcription": "thank you good bye", 
            "method-label": "finished", 
            "audio-file": "pt344x_0002978_0003068.wav", 
            "requested-slots": [], 
            "semantics": {
                "json": [
                    {
                        "slots": [], 
                        "act": "thankyou"
                    }, 
                    {
                        "slots": [], 
                        "act": "bye"
                    }
                ], 
                "cam": "thankyou()|bye()"
            }
        }
    ], 
    "task-information": {
        "goal": {
            "text": "Task 08055: You are looking for a cheap restaurant and it should be in the west part of town. You want to know the phone number.", 
            "request-slots": [
                "phone"
            ], 
            "constraints": [
                [
                    "pricerange", 
                    "cheap"
                ], 
                [
                    "area", 
                    "west"
                ]
            ]
        }, 
        "feedback": {
            "questionnaire": [
                [
                    "The system understood me well.", 
                    "agree"
                ]
            ], 
            "comments": null, 
            "success": true
        }
    }, 
    "session-id": "voip-7e07d8f0f5-20130327_181135"
}