{
    "caller-id": "31de0daa7b", 
    "turns": [
        {
            "turn-index": 0, 
            "goal-labels": {
                "food": "international", 
                "area": "south"
            }, 
            "transcription": "restaurant south part of town international food", 
            "method-label": "byconstraints", 
            "audio-file": "pt344x_0001291_0001660.wav", 
            "requested-slots": [], 
            "semantics": {
                "json": [
                    {
                        "slots": [
                            [
                                "food", 
                                "international"
                            ]
                        ], 
                        "act": "inform"
                    }, 
                    {
                        "slots": [
                            [
                                "area", 
                                "south"
                            ]
                        ], 
                        "act": "inform"
                    }
                ], 
                "cam": "inform(type=restaurant,area=south,food=international)"
            }
        }, 
        {
            "turn-index": 1, 
            "goal-labels": {
                "food": "international", 
                "area": "south"
            }, 
            "transcription": "yes", 
            "method-label": "byconstraints", 
            "audio-file": "pt344x_0002193_0002249.wav", 
            "requested-slots": [], 
            "semantics": {
                "json": [
                    {
                        "slots": [], 
                        "act": "affirm"
                    }
                ], 
                "cam": "affirm()"
            }
        }, 
        {
            "turn-index": 2, 
            "goal-labels": {
                "food": "international", 
                "area": "south"
            }, 
            "transcription": "modern europene", 
            "method-label": "byconstraints", 
            "audio-file": "pt344x_0002790_0002931.wav", 
            "requested-slots": [], 
            "semantics": {
                "json": [], 
                "cam": "null()"
            }
        }, 
        {
            "turn-index": 3, 
            "goal-labels": {
                "food": "international", 
                "area": "south"
            }, 
            "transcription": "address", 
            "method-label": "byconstraints", 
            "audio-file": "pt344x_0003677_0003770.wav", 
            "requested-slots": [
                "addr"
            ], 
            "semantics": {
                "json": [
                    {
                        "slots": [
                            [
                                "slot", 
                                "addr"
                            ]
                        ], 
                        "act": "request"
                    }
                ], 
                "cam": "request(addr)"
            }
        }, 
        {
            "turn-index": 4, 
            "goal-labels": {
                "food": "international", 
                "area": "south"
            }, 
            "transcription": "address", 
            "method-label": "byconstraints", 
            "audio-file": "pt344x_0004276_0004371.wav", 
            "requested-slots": [
                "addr"
            ], 
            "semantics": {
                "json": [
                    {
                        "slots": [
                            [
                                "slot", 
                                "addr"
                            ]
                        ], 
                        "act": "request"
                    }
                ], 
                "cam": "request(addr)"
            }
        }, 
        {
            "turn-index": 5, 
            "goal-labels": {
                "food": "international", 
                "area": "south"
            }, 
            "transcription": "phone number", 
            "method-label": "byconstraints", 
            "audio-file": "pt344x_0005133_0005226.wav", 
            "requested-slots": [
                "phone"
            ], 
            "semantics": {
                "json": [
                    {
                        "slots": [
                            [
                                "slot", 
                                "phone"
                            ]
                        ], 
                        "act": "request"
                    }
                ], 
                "cam": "request(phone)"
            }
        }, 
        {
            "turn-index": 6, 
            "goal-labels": {
                "food": "international", 
                "area": "south"
            }, 
            "transcription": "thank you good bye", 
            "method-label": "finished", 
            "audio-file": "pt344x_0006063_0006177.wav", 
            "requested-slots": [], 
            "semantics": {
                "json": [
                    {
                        "slots": [], 
                        "act": "thankyou"
                    }, 
                    {
                        "slots": [], 
                        "act": "bye"
                    }
                ], 
                "cam": "thankyou()|bye()"
            }
        }
    ], 
    "task-information": {
        "goal": {
            "text": "Task 01803: You are looking for a restaurant in the south part of town and it should serve international food. If there is no such venue how about modern european type of food. Make sure you get the address and phone number.", 
            "request-slots": [
                "addr", 
                "phone"
            ], 
            "constraints": [
                [
                    "food", 
                    "modern european"
                ], 
                [
                    "area", 
                    "south"
                ]
            ]
        }, 
        "feedback": {
            "questionnaire": [
                [
                    "The system understood me well.", 
                    "strongly agree"
                ]
            ], 
            "comments": null, 
            "success": true
        }
    }, 
    "session-id": "voip-31de0daa7b-20130401_205633"
}