{
    "caller-id": "5a464ca603", 
    "turns": [
        {
            "turn-index": 0, 
            "goal-labels": {
                "pricerange": "moderate", 
                "area": "west"
            }, 
            "transcription": "find me a moderately priced restaurant in the west part of town", 
            "method-label": "byconstraints", 
            "audio-file": "pt344x_0000950_0001273.wav", 
            "requested-slots": [], 
            "semantics": {
                "json": [
                    {
                        "slots": [
                            [
                                "pricerange", 
                                "moderate"
                            ]
                        ], 
                        "act": "inform"
                    }, 
                    {
                        "slots": [
                            [
                                "area", 
                                "west"
                            ]
                        ], 
                        "act": "inform"
                    }
                ], 
                "cam": "inform(pricerange=moderate,type=restaurant,area=west)"
            }
        }, 
        {
            "turn-index": 1, 
            "goal-labels": {
                "pricerange": "moderate", 
                "area": "west"
            }, 
            "transcription": "what is the phone number", 
            "method-label": "byconstraints", 
            "audio-file": "pt344x_0001876_0001973.wav", 
            "requested-slots": [
                "phone"
            ], 
            "semantics": {
                "json": [
                    {
                        "slots": [
                            [
                                "slot", 
                                "phone"
                            ]
                        ], 
                        "act": "request"
                    }
                ], 
                "cam": "request(phone)"
            }
        }, 
        {
            "turn-index": 2, 
            "goal-labels": {
                "pricerange": "moderate", 
                "area": "west"
            }, 
            "transcription": "thank you good bye", 
            "method-label": "finished", 
            "audio-file": "pt344x_0002777_0002833.wav", 
            "requested-slots": [], 
            "semantics": {
                "json": [
                    {
                        "slots": [], 
                        "act": "thankyou"
                    }, 
                    {
                        "slots": [], 
                        "act": "bye"
                    }
                ], 
                "cam": "thankyou()|bye()"
            }
        }
    ], 
    "task-information": {
        "goal": {
            "text": "Task 02100: You are looking for a moderately priced restaurant and it should be in the west part of town. Make sure you get the phone number.", 
            "request-slots": [
                "phone"
            ], 
            "constraints": [
                [
                    "pricerange", 
                    "moderate"
                ], 
                [
                    "area", 
                    "west"
                ]
            ]
        }, 
        "feedback": {
            "questionnaire": [
                [
                    "The system understood me well.", 
                    "strongly agree"
                ]
            ], 
            "comments": null, 
            "success": true
        }
    }, 
    "session-id": "voip-5a464ca603-20130401_165744"
}