{
    "caller-id": "199d62165b", 
    "turns": [
        {
            "turn-index": 0, 
            "goal-labels": {
                "pricerange": "cheap"
            }, 
            "transcription": "i am looking for a cheap restaurant", 
            "method-label": "byconstraints", 
            "audio-file": "pt344x_0000927_0001148.wav", 
            "requested-slots": [], 
            "semantics": {
                "json": [
                    {
                        "slots": [
                            [
                                "pricerange", 
                                "cheap"
                            ]
                        ], 
                        "act": "inform"
                    }
                ], 
                "cam": "inform(type=restaurant,pricerange=cheap,task=find)"
            }
        }, 
        {
            "turn-index": 1, 
            "goal-labels": {
                "pricerange": "cheap", 
                "area": "west"
            }, 
            "transcription": "and it should be in the west part of town", 
            "method-label": "byconstraints", 
            "audio-file": "pt344x_0001250_0001511.wav", 
            "requested-slots": [], 
            "semantics": {
                "json": [
                    {
                        "slots": [
                            [
                                "area", 
                                "west"
                            ]
                        ], 
                        "act": "inform"
                    }
                ], 
                "cam": "inform(area=west)"
            }
        }, 
        {
            "turn-index": 2, 
            "goal-labels": {
                "pricerange": "cheap", 
                "area": "west"
            }, 
            "transcription": "could i get the phone number please", 
            "method-label": "byconstraints", 
            "audio-file": "pt344x_0002130_0002292.wav", 
            "requested-slots": [
                "phone"
            ], 
            "semantics": {
                "json": [
                    {
                        "slots": [
                            [
                                "slot", 
                                "phone"
                            ]
                        ], 
                        "act": "request"
                    }
                ], 
                "cam": "request(phone)"
            }
        }, 
        {
            "turn-index": 3, 
            "goal-labels": {
                "pricerange": "cheap", 
                "area": "west"
            }, 
            "transcription": "thank you good bye", 
            "method-label": "finished", 
            "audio-file": "pt344x_0003120_0003231.wav", 
            "requested-slots": [], 
            "semantics": {
                "json": [
                    {
                        "slots": [], 
                        "act": "thankyou"
                    }, 
                    {
                        "slots": [], 
                        "act": "bye"
                    }
                ], 
                "cam": "thankyou()|bye()"
            }
        }
    ], 
    "task-information": {
        "goal": {
            "text": "Task 05868: You are looking for a cheap restaurant and it should be in the west part of town. Make sure you get the phone number.", 
            "request-slots": [
                "phone"
            ], 
            "constraints": [
                [
                    "pricerange", 
                    "cheap"
                ], 
                [
                    "area", 
                    "west"
                ]
            ]
        }, 
        "feedback": {
            "questionnaire": [
                [
                    "The system understood me well.", 
                    "strongly agree"
                ]
            ], 
            "comments": null, 
            "success": true
        }
    }, 
    "session-id": "voip-199d62165b-20130402_122354"
}